nuclino/__init__.py
nuclino/api/__init__.py
nuclino/api/client.py
nuclino/api/nuclino.py
nuclino/api/types.py
nuclino/api/utils.py
nuclino/api/endpoints/__init__.py
nuclino/api/endpoints/file.py
nuclino/api/endpoints/item.py
nuclino/api/endpoints/team.py
nuclino/api/endpoints/user.py
nuclino/api/endpoints/workspace.py
nuclino/api/exceptions/__init__.py
nuclino/api/exceptions/base.py
nuclino/api/exceptions/http.py
nuclino/models/__init__.py
nuclino/models/field.py
nuclino/models/file.py
nuclino/models/item.py
nuclino/models/shared.py
nuclino/models/team.py
nuclino/models/user.py
nuclino/models/workspace.py
nuclino-0.1.0.dist-info/METADATA
nuclino-0.1.0.dist-info/WHEEL
nuclino-0.1.0.dist-info/RECORD
