Metadata-Version: 2.4
Name: nuclino
Version: 0.1.0
Summary: Python client for the Nuclino API
Project-URL: Repository, https://github.com/whatisyourname0/nuclino
Project-URL: Documentation, https://github.com/whatisyourname0/nuclino#readme
Author-email: Joonho Lee <mynameisjune111@gmail.com>
License: MIT
Keywords: api,client,nuclino
Classifier: Development Status :: 4 - Beta
Classifier: Intended Audience :: Developers
Classifier: License :: OSI Approved :: MIT License
Classifier: Programming Language :: Python :: 3
Classifier: Programming Language :: Python :: 3.13
Requires-Python: >=3.12
Requires-Dist: ratelimit>=2.2.1
Requires-Dist: requests>=2.32.3
